{
  "Cancel": "Cancel",
  "Edit": "Edit",
  "Firstname": "Firstname",
  "Lastname": "Lastname",
  "Lorem-layout": "Lorem-layout",
  "Profile page": "Profile page",
  "ProfileError": "ProfileError",
  "ProfileErrorText": "ProfileErrorText",
  "ProfileErrorTitle": "ProfileErrorTitle",
  "RefreshPage": "RefreshPage",
  "UserProfile": "UserProfile",
  "Your name": "Your name",
  "decr": "decr",
  "incr": "incr",
  "Авторизация": "Авторизация",
  "Введите логин": "Введите логин",
  "Введите пароль": "Введите пароль",
  "Войти": "Войти",
  "Вход": "Вход",
  "Выйти": "Выйти",
  "Главная": "Главная",
  "Главная страница": "Главная страница",
  "Короткий язык": "Короткий язык",
  "Меню": "Меню",
  "Нажмите для ошибки": "Нажмите для ошибки",
  "Некорректные данные": "Некорректные данные",
  "Непредвиденная ошибка": "Непредвиденная ошибка",
  "Нжмите для ошибки": "Нжмите для ошибки",
  "О сайте": "О сайте",
  "Обновить страницу": "Обновить страницу",
  "Перевод": "Перевод",
  "Страница отсутствует": "Страница отсутствует",
  "Тестовый пример": "Тестовый пример",
  "Язык": "Рус"
}
